netZooPy/__init__.py
netZooPy/cli.py
netZooPy/command_line.py
netZooPy/bonobo/__init__.py
netZooPy/bonobo/bonobo.py
netZooPy/bonobo/io.py
netZooPy/bonobo/timer.py
netZooPy/cobra/__init__.py
netZooPy/cobra/cobra.py
netZooPy/condor/__init__.py
netZooPy/condor/condor.py
netZooPy/condor/timer.py
netZooPy/dragon/__init__.py
netZooPy/dragon/dragon.py
netZooPy/giraffe/__init__.py
netZooPy/giraffe/giraffe.py
netZooPy/giraffe/utils.py
netZooPy/lioness/__init__.py
netZooPy/lioness/analyze_lioness.py
netZooPy/lioness/io.py
netZooPy/lioness/lioness.py
netZooPy/lioness/lioness_for_dragon.py
netZooPy/lioness/lioness_for_otter.py
netZooPy/lioness/lioness_for_puma.py
netZooPy/lioness/onlineCoexpression.py
netZooPy/lioness/run_lioness.py
netZooPy/lioness/timer.py
netZooPy/otter/__init__.py
netZooPy/otter/otter.py
netZooPy/panda/__init__.py
netZooPy/panda/analyze_panda.py
netZooPy/panda/calculations.py
netZooPy/panda/calculations_gpu.py
netZooPy/panda/io.py
netZooPy/panda/panda.py
netZooPy/panda/run_panda.py
netZooPy/panda/timer.py
netZooPy/puma/__init__.py
netZooPy/puma/calculations.py
netZooPy/puma/calculations_gpu.py
netZooPy/puma/puma.py
netZooPy/puma/run_puma.py
netZooPy/puma/timer.py
netZooPy/sambar/__init__.py
netZooPy/sambar/sambar.py
netzoopy-0.11.0.dist-info/licenses/LICENSE
netzoopy-0.11.0.dist-info/METADATA
netzoopy-0.11.0.dist-info/WHEEL
netzoopy-0.11.0.dist-info/entry_points.txt
netzoopy-0.11.0.dist-info/top_level.txt
netzoopy-0.11.0.dist-info/RECORD
