Metadata-Version: 2.4
Name: netZooPy
Version: 0.11.0
Summary: Python implementation of netZoo
Home-page: https://github.com/netZoo/netZooPy
Author: netZoo team
Author-email: vfanfani@hsph.harvard.edu
License: GPL-3
License-File: LICENSE
Requires-Dist: h5py
Requires-Dist: pandas
Requires-Dist: numpy<2.0,>=1.19.2
Requires-Dist: networkx>=2.6.3
Requires-Dist: matplotlib>=3.3.4
Requires-Dist: scipy>=1.5.3
Requires-Dist: igraph
Requires-Dist: joblib>=1.1.0
Requires-Dist: statsmodels>=0.12.2
Requires-Dist: click
Requires-Dist: tables
Requires-Dist: torch
Dynamic: author
Dynamic: author-email
Dynamic: description
Dynamic: description-content-type
Dynamic: home-page
Dynamic: license
Dynamic: license-file
Dynamic: requires-dist
Dynamic: summary
